odoo/addons/l10n_br_sale_commission/README.rst
odoo/addons/l10n_br_sale_commission/__init__.py
odoo/addons/l10n_br_sale_commission/__manifest__.py
odoo/addons/l10n_br_sale_commission/demo/res_config_settings_demo.xml
odoo/addons/l10n_br_sale_commission/demo/sale_order_demo.xml
odoo/addons/l10n_br_sale_commission/i18n/l10n_br_commission.pot
odoo/addons/l10n_br_sale_commission/i18n/l10n_br_sale_commission.pot
odoo/addons/l10n_br_sale_commission/i18n/pt_BR.po
odoo/addons/l10n_br_sale_commission/models/__init__.py
odoo/addons/l10n_br_sale_commission/models/account_invoice_line.py
odoo/addons/l10n_br_sale_commission/models/res_config_settings.py
odoo/addons/l10n_br_sale_commission/models/sale_order_line.py
odoo/addons/l10n_br_sale_commission/models/settlement.py
odoo/addons/l10n_br_sale_commission/readme/CONFIGURE.rst
odoo/addons/l10n_br_sale_commission/readme/CONTRIBUTORS.rst
odoo/addons/l10n_br_sale_commission/readme/DESCRIPTION.rst
odoo/addons/l10n_br_sale_commission/readme/HISTORY.rst
odoo/addons/l10n_br_sale_commission/readme/INSTALL.rst
odoo/addons/l10n_br_sale_commission/readme/ROADMAP.rst
odoo/addons/l10n_br_sale_commission/readme/USAGE.rst
odoo/addons/l10n_br_sale_commission/static/description/icon.png
odoo/addons/l10n_br_sale_commission/static/description/index.html
odoo/addons/l10n_br_sale_commission/tests/__init__.py
odoo/addons/l10n_br_sale_commission/tests/test_l10n_br_sale_commission.py
odoo/addons/l10n_br_sale_commission/views/res_config_settings_views.xml
odoo/addons/l10n_br_sale_commission/wizards/__init__.py
odoo/addons/l10n_br_sale_commission/wizards/wizard_invoice.py
odoo/addons/l10n_br_sale_commission/wizards/wizard_invoice.xml
odoo14_addon_l10n_br_sale_commission-14.0.1.0.1.dist-info/METADATA
odoo14_addon_l10n_br_sale_commission-14.0.1.0.1.dist-info/WHEEL
odoo14_addon_l10n_br_sale_commission-14.0.1.0.1.dist-info/top_level.txt
odoo14_addon_l10n_br_sale_commission-14.0.1.0.1.dist-info/RECORD
